{
    "body": "create new package",
    "user": "Sinan81",
    "url": "https://api.github.com/repos/spack/spack/issues/7588",
    "updated_at": "2018-03-26 00:55:23",
    "created_at": "2018-03-24 10:04:40",
    "closed_at": "2018-03-25 13:50:18",
    "state": "closed",
    "title": "new package: Seqan (bioinformatics)",
    "number": 7588,
    "milestone": null,
    "labels": [
        "new-package"
    ],
    "id": 308246233,
    "html_url": "https://github.com/spack/spack/pull/7588",
    "assignees": [],
    "comments": 0
}