{
    "body": "added NOAA maintainers, set environment vars frequently used with bacio in UFS builds",
    "user": "edwardhartnett",
    "url": "https://api.github.com/repos/spack/spack/issues/26069",
    "updated_at": "2021-12-08 14:58:44",
    "created_at": "2021-09-20 14:31:24",
    "closed_at": "2021-12-08 14:58:44",
    "state": "closed",
    "title": "added NOAA maintainers, set environment vars frequently used with bacio in UFS builds",
    "number": 26069,
    "milestone": null,
    "labels": [
        "update-package",
        "maintainers"
    ],
    "id": 1001041462,
    "html_url": "https://github.com/spack/spack/pull/26069",
    "assignees": [],
    "comments": 3
}