{
    "body": "This fixes:\r\n\r\n```\r\n==> No patches needed for fast-global-file-status\r\n==> fast-global-file-status: Executing phase: 'autoreconf'\r\n==> Error: AttributeError: module 'spack.pkg.builtin.fast-global-file-status' has no attribute 'autoreconf'\r\n\r\n/home/atosla/Tools/spack/lib/spack/spack/build_systems/autotools.py:277, in autoreconf:\r\n        274            # --install, --verbose, --force\r\n        275            autoreconf_args = ['-ivf']\r\n        276            autoreconf_args += self.autoreconf_search_path_args\r\n  >>    277            autoreconf_args += self.autoreconf_extra_args\r\n        278            m.autoreconf(*autoreconf_args)\r\n```",
    "user": "lee218llnl",
    "url": "https://api.github.com/repos/spack/spack/issues/26005",
    "updated_at": "2021-09-21 11:41:01",
    "created_at": "2021-09-16 19:58:30",
    "closed_at": "2021-09-21 11:41:00",
    "state": "closed",
    "title": "fgfs: fix missing autotools depends_on",
    "number": 26005,
    "milestone": null,
    "labels": [
        "dependencies",
        "update-package"
    ],
    "id": 998588867,
    "html_url": "https://github.com/spack/spack/pull/26005",
    "assignees": [
        "sethrj"
    ],
    "comments": 3
}