{
    "body": "The download url changed and needs to be corrected.",
    "user": "eschnett",
    "url": "https://api.github.com/repos/spack/spack/issues/3322",
    "updated_at": "2017-03-06 14:21:51",
    "created_at": "2017-03-02 20:36:24",
    "closed_at": "2017-03-03 22:29:57",
    "state": "closed",
    "title": "opencoarrays: Correct download url, update version",
    "number": 3322,
    "milestone": null,
    "labels": [],
    "id": 211509676,
    "html_url": "https://github.com/spack/spack/pull/3322",
    "assignees": [],
    "comments": 0
}