{
    "body": "",
    "user": "weijianwen",
    "url": "https://api.github.com/repos/spack/spack/issues/8028",
    "updated_at": "2018-05-14 13:31:42",
    "created_at": "2018-05-05 02:35:42",
    "closed_at": "2018-05-05 22:16:48",
    "state": "closed",
    "title": "A new library: libshm.",
    "number": 8028,
    "milestone": null,
    "labels": [
        "new-package"
    ],
    "id": 320472862,
    "html_url": "https://github.com/spack/spack/pull/8028",
    "assignees": [],
    "comments": 0
}