{
    "body": "I've specified several implementations of mpi which are currently installed on my local computing cluster in packages.yaml.\r\n\r\nWhen I run `spack find` it only lists packages which were explicitly built by spack itself, and doesn't mention these packages.\r\n\r\nI think it would be good to also mention these packages or provide some kind of option to spack find to mention them as it helps verify that spack knows about these modules.",
    "user": "krafczyk",
    "url": "https://api.github.com/repos/spack/spack/issues/2191",
    "updated_at": "2017-07-04 06:03:34",
    "created_at": "2016-10-31 20:56:33",
    "closed_at": "2017-07-03 15:56:38",
    "state": "closed",
    "title": "spack find currently doesn't show packages which were specified as already installed in packages.yaml",
    "number": 2191,
    "milestone": null,
    "labels": [],
    "id": 186395452,
    "html_url": "https://github.com/spack/spack/issues/2191",
    "assignees": [
        "alalazo"
    ],
    "comments": 6
}