{
    "body": "The goal of the libpfm4 project is now to develop a user library called libpfm4 to help setup performance events for use with the perf_events Linux kernel interface. The development of the perfmon kernel subsystem, libpfm and pfmon has now stopped.",
    "user": "weijianwen",
    "url": "https://api.github.com/repos/spack/spack/issues/3667",
    "updated_at": "2017-04-03 16:37:28",
    "created_at": "2017-04-03 14:44:25",
    "closed_at": "2017-04-03 15:59:25",
    "state": "closed",
    "title": "Add libpfm4 package.",
    "number": 3667,
    "milestone": null,
    "labels": [
        "new-package"
    ],
    "id": 218956638,
    "html_url": "https://github.com/spack/spack/pull/3667",
    "assignees": [],
    "comments": 0
}