{
    "body": "",
    "user": "glennpj",
    "url": "https://api.github.com/repos/spack/spack/issues/15221",
    "updated_at": "2020-02-28 15:15:11",
    "created_at": "2020-02-26 03:42:05",
    "closed_at": "2020-02-28 02:12:32",
    "state": "closed",
    "title": "new package: py-auxlib",
    "number": 15221,
    "milestone": null,
    "labels": [
        "new-package"
    ],
    "id": 571048938,
    "html_url": "https://github.com/spack/spack/pull/15221",
    "assignees": [],
    "comments": 0
}