{
    "body": "This PR adds a `perf` variant (disabled by default) to Julia that is able to generate `perf` data for [external profiling](https://docs.julialang.org/en/v1/manual/profile/#External-Profiling-1).",
    "user": "zzzoom",
    "url": "https://api.github.com/repos/spack/spack/issues/16740",
    "updated_at": "2021-02-24 04:24:02",
    "created_at": "2020-05-20 08:31:22",
    "closed_at": "2021-02-24 04:24:01",
    "state": "closed",
    "title": "julia: Add perf profiling support",
    "number": 16740,
    "milestone": null,
    "labels": [
        "new-variant"
    ],
    "id": 621567862,
    "html_url": "https://github.com/spack/spack/pull/16740",
    "assignees": [],
    "comments": 8
}