{
    "body": "Successfully builds and passes import tests on macOS 10.15.7 with Python 3.8.11 and Apple Clang 12.0.0.",
    "user": "adamjstewart",
    "url": "https://api.github.com/repos/spack/spack/issues/24715",
    "updated_at": "2021-07-06 13:02:11",
    "created_at": "2021-07-05 19:41:36",
    "closed_at": "2021-07-06 06:40:12",
    "state": "closed",
    "title": "py-black: add new versions",
    "number": 24715,
    "milestone": null,
    "labels": [
        "new-version",
        "python",
        "dependencies",
        "update-package",
        "new-variant"
    ],
    "id": 937327909,
    "html_url": "https://github.com/spack/spack/pull/24715",
    "assignees": [],
    "comments": 0
}