{
    "body": "Added Emacs package.\n\nQ: What to do about Emacs dependencies on the window system, libtiff, etc.  For now, I just assume Emacs will pick them all up from the system.  This is a fair assumption: Emacs is just for using, not linking against; we will be less particular about its dependencies.\n",
    "user": "citibeth",
    "url": "https://api.github.com/repos/spack/spack/issues/528",
    "updated_at": "2016-03-12 03:30:09",
    "created_at": "2016-03-10 02:30:57",
    "closed_at": "2016-03-11 21:31:58",
    "state": "closed",
    "title": "Added Emacs package",
    "number": 528,
    "milestone": null,
    "labels": [],
    "id": 139764776,
    "html_url": "https://github.com/spack/spack/pull/528",
    "assignees": [],
    "comments": 1
}