{
    "body": "The build requires libiconv (but still it doesn't find it when not providing LDFLAGS).\r\n\r\nRegarding the LDFLAGS: A patch to the configure flow would be the better solution\u2026",
    "user": "muffgaga",
    "url": "https://api.github.com/repos/spack/spack/issues/7611",
    "updated_at": "2018-04-08 18:16:34",
    "created_at": "2018-03-27 14:38:35",
    "closed_at": "2018-04-06 20:46:48",
    "state": "closed",
    "title": "Fix build of xerces-c",
    "number": 7611,
    "milestone": null,
    "labels": [
        "dependencies"
    ],
    "id": 308998344,
    "html_url": "https://github.com/spack/spack/pull/7611",
    "assignees": [],
    "comments": 1
}