{
    "body": "This PR makes the following modifications to run-flake8:\n- Run flake8 checks on changed files that haven't been committed yet\n- Allow `run-flake8` to be run from any directory, not just `$SPACK_ROOT`\n- Always clean up temporary package.py files, even if the user hits <kbd>Ctrl</kbd>-<kbd>C</kbd>\n",
    "user": "adamjstewart",
    "url": "https://api.github.com/repos/spack/spack/issues/1480",
    "updated_at": "2016-08-11 17:31:43",
    "created_at": "2016-08-09 18:46:02",
    "closed_at": "2016-08-11 17:31:43",
    "state": "closed",
    "title": "Various improvements to run-flake8",
    "number": 1480,
    "milestone": null,
    "labels": [],
    "id": 170241225,
    "html_url": "https://github.com/spack/spack/pull/1480",
    "assignees": [],
    "comments": 2
}