{
    "body": "Download package version with a configure script. This avoids having to use autoconf, which requires many m4 scripts that are not always available.\n\nCloses #313.\n",
    "user": "eschnett",
    "url": "https://api.github.com/repos/spack/spack/issues/314",
    "updated_at": "2016-01-12 19:45:38",
    "created_at": "2016-01-08 19:24:07",
    "closed_at": "2016-01-12 17:14:19",
    "state": "closed",
    "title": "Build libpciaccess from tarball",
    "number": 314,
    "milestone": null,
    "labels": [],
    "id": 125676027,
    "html_url": "https://github.com/spack/spack/pull/314",
    "assignees": [],
    "comments": 4
}