{
    "body": "Add test method and Fix #21500",
    "user": "takanori-ihara",
    "url": "https://api.github.com/repos/spack/spack/issues/21692",
    "updated_at": "2021-02-22 20:54:24",
    "created_at": "2021-02-16 02:42:41",
    "closed_at": "2021-02-22 09:36:44",
    "state": "closed",
    "title": "eigenexa: Add test method and Fix #21500",
    "number": 21692,
    "milestone": null,
    "labels": [],
    "id": 808939079,
    "html_url": "https://github.com/spack/spack/pull/21692",
    "assignees": [],
    "comments": 1
}