{
    "body": "Use `h5cc -showconfig` to detect external HDF5 installations.\r\n\r\nNote that Spack-installed HDF5 has issue https://github.com/spack/spack/issues/27000, so can't currently be found with this method. Other installations, e.g. Homebrew on macOS, can be found.",
    "user": "nilsvu",
    "url": "https://api.github.com/repos/spack/spack/issues/28569",
    "updated_at": "2022-01-24 16:34:22",
    "created_at": "2022-01-24 09:28:06",
    "closed_at": "None",
    "state": "open",
    "title": "hdf5: find external",
    "number": 28569,
    "milestone": null,
    "labels": [
        "update-package"
    ],
    "id": 1112382935,
    "html_url": "https://github.com/spack/spack/pull/28569",
    "assignees": [],
    "comments": 2
}