{
    "body": "UPDATE:\r\n\r\nWas supposed to help with #3501 but doesn't solve the real problem.",
    "user": "adamjstewart",
    "url": "https://api.github.com/repos/spack/spack/issues/3502",
    "updated_at": "2017-03-21 20:59:14",
    "created_at": "2017-03-20 21:45:59",
    "closed_at": "2017-03-20 23:08:46",
    "state": "closed",
    "title": "Fix: setuptools is a runtime dependency for pudb",
    "number": 3502,
    "milestone": null,
    "labels": [],
    "id": 215564951,
    "html_url": "https://github.com/spack/spack/pull/3502",
    "assignees": [],
    "comments": 14
}