{
    "body": "This pull request adds:\n- Several new versions of Python including a switch in the preferred to 2.7.12\n- Changes in how the ucs4 variants configure arguments are applied\n",
    "user": "paulhopkins",
    "url": "https://api.github.com/repos/spack/spack/issues/1187",
    "updated_at": "2016-07-15 21:04:47",
    "created_at": "2016-07-07 12:20:35",
    "closed_at": "2016-07-15 21:04:47",
    "state": "closed",
    "title": "Bugfix/python updates",
    "number": 1187,
    "milestone": null,
    "labels": [],
    "id": 164296119,
    "html_url": "https://github.com/spack/spack/pull/1187",
    "assignees": [],
    "comments": 6
}