{
    "body": "",
    "user": "Try2Code",
    "url": "https://api.github.com/repos/spack/spack/issues/10945",
    "updated_at": "2019-03-26 19:34:33",
    "created_at": "2019-03-20 15:57:18",
    "closed_at": "2019-03-26 19:34:33",
    "state": "closed",
    "title": "updated ruby package to current release version 2.6.2",
    "number": 10945,
    "milestone": null,
    "labels": [],
    "id": 423333727,
    "html_url": "https://github.com/spack/spack/pull/10945",
    "assignees": [],
    "comments": 0
}