{
    "body": "@tgamblin I'm not sure how much longer I can keep doing this. How much work would it be to make a bot that pops up on a PR and says \"don't forget to update the tab completion script!\" every time someone edits a file in `lib/spack/spack/cmd`?\r\n\r\n@JBlaschke please use this version when you start working on your fish tab completion script.",
    "user": "adamjstewart",
    "url": "https://api.github.com/repos/spack/spack/issues/14392",
    "updated_at": "2020-01-07 05:18:36",
    "created_at": "2020-01-06 06:40:29",
    "closed_at": "2020-01-07 05:18:14",
    "state": "closed",
    "title": "Fix outdated bash tab completion",
    "number": 14392,
    "milestone": null,
    "labels": [
        "shell-support"
    ],
    "id": 545567259,
    "html_url": "https://github.com/spack/spack/pull/14392",
    "assignees": [],
    "comments": 4
}