{
    "body": "This package is a requirement for py-merlinwf",
    "user": "koning",
    "url": "https://api.github.com/repos/spack/spack/issues/13852",
    "updated_at": "2019-11-25 22:56:35",
    "created_at": "2019-11-22 19:10:03",
    "closed_at": "2019-11-25 22:56:35",
    "state": "closed",
    "title": "Add the py-coloredlogs package",
    "number": 13852,
    "milestone": null,
    "labels": [
        "new-package"
    ],
    "id": 527366810,
    "html_url": "https://github.com/spack/spack/pull/13852",
    "assignees": [],
    "comments": 1
}