{
    "body": "Adds explanation to `spack spec -h` for the `[^]` symbol present when using an upstream spack instance.",
    "user": "jfinney10",
    "url": "https://api.github.com/repos/spack/spack/issues/23758",
    "updated_at": "2021-05-19 07:49:07",
    "created_at": "2021-05-18 19:38:13",
    "closed_at": "2021-05-19 07:49:07",
    "state": "closed",
    "title": "Add caret/hat to spack spec help documentation",
    "number": 23758,
    "milestone": null,
    "labels": [],
    "id": 894714411,
    "html_url": "https://github.com/spack/spack/pull/23758",
    "assignees": [],
    "comments": 1
}