{
    "body": "---\n\nNot sure about the second commit; can back it out if wanted.\n\nCc: @davydden @tgamblin \n",
    "user": "mathstuf",
    "url": "https://api.github.com/repos/spack/spack/issues/818",
    "updated_at": "2016-04-23 20:35:05",
    "created_at": "2016-04-21 18:20:05",
    "closed_at": "2016-04-23 20:34:51",
    "state": "closed",
    "title": "Spack compiler find",
    "number": 818,
    "milestone": null,
    "labels": [],
    "id": 150151298,
    "html_url": "https://github.com/spack/spack/pull/818",
    "assignees": [],
    "comments": 3
}