{
    "body": "#5387 should be merged before this.\r\n\r\n- [x] converted `log_path` and `env_path` to properties of PackageBase.\r\n- [x] InstallErrors in build_environment are now annotated with the package\r\n  that caused them, in the 'pkg' attribute.\r\n- [x] Add `--show-log-on-error` option to `spack install` that catches\r\n  InstallErrors and prints the log to stderr if it exists.\r\n\r\nNote that adding a reference to the Pakcage allows a lot of stuff\r\ncurrently handled by do_install() and build_environment to be handled\r\nexternally.\r\n\r\n@pramodskumbhar: does this do what you wanted in #5016?\r\n\r\n@alalazo @adamjstewart ",
    "user": "tgamblin",
    "url": "https://api.github.com/repos/spack/spack/issues/5388",
    "updated_at": "2017-09-18 14:51:47",
    "created_at": "2017-09-17 22:19:58",
    "closed_at": "2017-09-18 01:52:26",
    "state": "closed",
    "title": "Add --show-log-on-error option to `spack install`",
    "number": 5388,
    "milestone": null,
    "labels": [],
    "id": 258340059,
    "html_url": "https://github.com/spack/spack/pull/5388",
    "assignees": [],
    "comments": 1
}