{
    "body": "Fixes #1706. \n- moved ensure_dicts() call from Package.**init** to Package.**metaclass**.\n",
    "user": "tgamblin",
    "url": "https://api.github.com/repos/spack/spack/issues/1718",
    "updated_at": "2016-09-02 22:10:30",
    "created_at": "2016-09-02 21:51:00",
    "closed_at": "2016-09-02 22:10:30",
    "state": "closed",
    "title": "Attributes for directives need to be set at class creation time.",
    "number": 1718,
    "milestone": null,
    "labels": [],
    "id": 174854549,
    "html_url": "https://github.com/spack/spack/pull/1718",
    "assignees": [],
    "comments": 0
}