{
    "body": "\u2026naming\r\n\r\nRules N813 and N814 prevented import statements like this:\r\n\r\n  xml.etree.ElementTree as et\r\n  xml.etree.ElementTree as ET\r\n\r\nBut both of those seem pretty reasonable.  We see no reason to require\r\nany camelcase import to be imported \"as\" a camelcase word.",
    "user": "tgamblin",
    "url": "https://api.github.com/repos/spack/spack/issues/11477",
    "updated_at": "2019-05-16 14:06:20",
    "created_at": "2019-05-15 22:07:53",
    "closed_at": "2019-05-16 07:47:03",
    "state": "closed",
    "title": "flake8: exceptions for pedantic camelcase rules from pep8-naming",
    "number": 11477,
    "milestone": null,
    "labels": [],
    "id": 444667020,
    "html_url": "https://github.com/spack/spack/pull/11477",
    "assignees": [],
    "comments": 4
}