{
    "body": "Closes #25900 ",
    "user": "sethrj",
    "url": "https://api.github.com/repos/spack/spack/issues/25911",
    "updated_at": "2021-12-20 12:13:29",
    "created_at": "2021-09-13 10:54:59",
    "closed_at": "2021-09-13 14:51:39",
    "state": "closed",
    "title": "trilinos: add conflicts for fortran",
    "number": 25911,
    "milestone": null,
    "labels": [
        "update-package",
        "conflicts"
    ],
    "id": 994743983,
    "html_url": "https://github.com/spack/spack/pull/25911",
    "assignees": [],
    "comments": 0
}