{
    "body": "this is the first version that builds without patching",
    "user": "aumuell",
    "url": "https://api.github.com/repos/spack/spack/issues/23985",
    "updated_at": "2021-05-28 09:23:47",
    "created_at": "2021-05-28 08:34:45",
    "closed_at": "2021-05-28 09:23:47",
    "state": "closed",
    "title": "ispc: add 1.15.0",
    "number": 23985,
    "milestone": null,
    "labels": [],
    "id": 904951269,
    "html_url": "https://github.com/spack/spack/pull/23985",
    "assignees": [],
    "comments": 0
}