{
    "body": "Module/FindDoxygen.cmake uses Windows based directory for file globbing that create issues on Linux.  I removed that code on Linux.",
    "user": "serbanmaerean",
    "url": "https://api.github.com/repos/spack/spack/issues/4612",
    "updated_at": "2017-07-02 13:31:44",
    "created_at": "2017-06-27 03:19:43",
    "closed_at": "2017-07-02 13:31:44",
    "state": "closed",
    "title": "Fix linux/cmake",
    "number": 4612,
    "milestone": null,
    "labels": [
        "cmake"
    ],
    "id": 238726940,
    "html_url": "https://github.com/spack/spack/pull/4612",
    "assignees": [],
    "comments": 8
}