{
    "body": "",
    "user": "matthiasdiener",
    "url": "https://api.github.com/repos/spack/spack/issues/20047",
    "updated_at": "2020-11-24 04:01:41",
    "created_at": "2020-11-22 18:18:52",
    "closed_at": "2020-11-24 02:27:56",
    "state": "closed",
    "title": "charmpp: fix tests",
    "number": 20047,
    "milestone": null,
    "labels": [
        "update-package",
        "maintainers"
    ],
    "id": 748309116,
    "html_url": "https://github.com/spack/spack/pull/20047",
    "assignees": [],
    "comments": 2
}