{
    "body": "* The CLAW compiler uses the native compiler preprocessing capabilities therefore, the raw path of the compiler is needed to configure the CLAW Compiler and not the Spack wrapper. \r\n\r\nThanks @jrood-nrel to point out this problem",
    "user": "clementval",
    "url": "https://api.github.com/repos/spack/spack/issues/9748",
    "updated_at": "2018-11-08 09:11:27",
    "created_at": "2018-11-07 13:20:52",
    "closed_at": "2018-11-07 14:24:25",
    "state": "closed",
    "title": "Use the raw compiler path for the preprocessing pass in CLAW driver",
    "number": 9748,
    "milestone": null,
    "labels": [
        "update-package"
    ],
    "id": 378284592,
    "html_url": "https://github.com/spack/spack/pull/9748",
    "assignees": [],
    "comments": 1
}