{
    "body": "",
    "user": "qwertos",
    "url": "https://api.github.com/repos/spack/spack/issues/15770",
    "updated_at": "2020-04-07 16:21:50",
    "created_at": "2020-03-30 22:41:17",
    "closed_at": "2020-04-07 16:21:50",
    "state": "closed",
    "title": "New package: boinc-client",
    "number": 15770,
    "milestone": null,
    "labels": [
        "new-package"
    ],
    "id": 590646813,
    "html_url": "https://github.com/spack/spack/pull/15770",
    "assignees": [],
    "comments": 1
}