{
    "body": "This PR fixes an issue when using xcb-proto in an environment with python 3.9. xcb-proto uses fractions.gcd which has been deprecated since python 3.5 and was removed in python 3.9. \r\n\r\nSee\r\nhttps://docs.python.org/3.5/library/math.html#math.gcd",
    "user": "sly2j",
    "url": "https://api.github.com/repos/spack/spack/issues/20793",
    "updated_at": "2021-01-12 18:45:12",
    "created_at": "2021-01-12 14:43:05",
    "closed_at": "None",
    "state": "open",
    "title": "fractions.gcd was removed in python 3.9, use math.gcd instead",
    "number": 20793,
    "milestone": null,
    "labels": [
        "python3",
        "patch"
    ],
    "id": 784298324,
    "html_url": "https://github.com/spack/spack/pull/20793",
    "assignees": [],
    "comments": 0
}