{
    "body": "Change Ants to ANTs to match software name",
    "user": "simonflood",
    "url": "https://api.github.com/repos/spack/spack/issues/7827",
    "updated_at": "2018-04-20 10:46:58",
    "created_at": "2018-04-19 16:11:17",
    "closed_at": "2018-04-19 17:53:32",
    "state": "closed",
    "title": "Correct ANTs package class",
    "number": 7827,
    "milestone": null,
    "labels": [],
    "id": 315945310,
    "html_url": "https://github.com/spack/spack/pull/7827",
    "assignees": [],
    "comments": 2
}