{
    "body": "- Fixes a typo in `root_cmakelists_dir` for `fenics-basix`\r\n- Fixes a dependency range in `py-fenics-dolfinx`\r\n- Updates maintainers for  `fenics-dolfinx` and  `py-fenics-dolfinx`\r\n\r\nChanges have been tested. ",
    "user": "garth-wells",
    "url": "https://api.github.com/repos/spack/spack/issues/26445",
    "updated_at": "2021-10-04 07:20:54",
    "created_at": "2021-10-03 17:54:43",
    "closed_at": "2021-10-04 07:20:54",
    "state": "closed",
    "title": "FEniCSx: fix CMake root directory and dependency versions",
    "number": 26445,
    "milestone": null,
    "labels": [
        "python",
        "dependencies",
        "update-package",
        "maintainers"
    ],
    "id": 1014475769,
    "html_url": "https://github.com/spack/spack/pull/26445",
    "assignees": [],
    "comments": 1
}