{
    "body": "See Issue [2990](https://github.com/LLNL/spack/issues/2990) for background.\r\n\r\nVersions of cmake through 3.6.9 seem to need OpenSSL up to 1.0.99.  Later\r\nversions can use the current release (thanks to @citibeth for\r\n[digging up details](https://cmake.org/pipermail/cmake/2016-November/064631.html)).\r\n\r\n@davydden suggested this change.\r\n\r\nWithout it I *am not* able to build `cmake@3.6.1` on CentOS 7 and I *am*\r\nable to build `cmake@3.7.2`.\r\n\r\nWith this change I am able to build both `cmake@3.6.1` and `cmake@3.7.2`\r\non CentOS 7.\r\n\r\nCloses #2990.",
    "user": "hartzell",
    "url": "https://api.github.com/repos/spack/spack/issues/2993",
    "updated_at": "2017-02-03 22:35:16",
    "created_at": "2017-02-01 22:11:32",
    "closed_at": "2017-02-03 22:35:16",
    "state": "closed",
    "title": "Different versions of cmake need diff vers of openssl",
    "number": 2993,
    "milestone": null,
    "labels": [
        "new-package",
        "cmake"
    ],
    "id": 204721061,
    "html_url": "https://github.com/spack/spack/pull/2993",
    "assignees": [],
    "comments": 0
}