{
    "body": "As a user of Spack I want `environment-modules` v4.X to be supported as a module command so that I can use Spack shell integration with the latest version available.\r\n\r\n### Rationale\r\n\r\nUsers that want to use Spack's shell integration should be able to employ the latest major version of `environment-modules`.\r\n\r\n### Description\r\n\r\nThere's a PR that is mostly done to permit this integration, see #7536.",
    "user": "alalazo",
    "url": "https://api.github.com/repos/spack/spack/issues/10708",
    "updated_at": "2019-02-28 12:22:44",
    "created_at": "2019-02-26 09:28:47",
    "closed_at": "2019-02-28 12:22:44",
    "state": "closed",
    "title": "Permit Spack shell integration with Modules v4",
    "number": 10708,
    "milestone": null,
    "labels": [
        "feature",
        "modules"
    ],
    "id": 414511613,
    "html_url": "https://github.com/spack/spack/issues/10708",
    "assignees": [
        "alalazo"
    ],
    "comments": 0
}