{
    "body": "UnifyFS has been integrated with updated versions of its mochi-margo dependency (and mochi-margo's mercury and libfabric dependencies).\r\n\r\nThese changes are to allow unifyfs@develop to use these updated versions and to prep for an upcoming unifyfs release.\r\n\r\nAlso removes unsupported 0.9.0 version and associated variant, dependencies, and patch.",
    "user": "CamStan",
    "url": "https://api.github.com/repos/spack/spack/issues/22390",
    "updated_at": "2021-04-21 18:32:20",
    "created_at": "2021-03-18 19:13:42",
    "closed_at": "2021-04-21 17:20:42",
    "state": "closed",
    "title": "unifyfs: dependency updates",
    "number": 22390,
    "milestone": null,
    "labels": [
        "patch",
        "conflicts",
        "ecp",
        "e4s"
    ],
    "id": 835159540,
    "html_url": "https://github.com/spack/spack/pull/22390",
    "assignees": [
        "scheibelp"
    ],
    "comments": 6
}