{
    "body": "Fixes https://github.com/spack/spack/issues/19825\r\n\r\nWhen invoking `buildcache list` multiple times, the command was reporting no specs in the cache the second time around. The presence of an up-to-date index was causing the internal representation to be left un-initialized.\r\n\r\nSee also: https://github.com/spack/spack/pull/19209",
    "user": "scheibelp",
    "url": "https://api.github.com/repos/spack/spack/issues/19848",
    "updated_at": "2020-11-12 18:19:35",
    "created_at": "2020-11-10 20:34:55",
    "closed_at": "2020-11-11 07:24:19",
    "state": "closed",
    "title": "Binary caching: fix buildcache list (multiple invocations)",
    "number": 19848,
    "milestone": null,
    "labels": [],
    "id": 740224350,
    "html_url": "https://github.com/spack/spack/pull/19848",
    "assignees": [],
    "comments": 0
}