{
    "body": "- grep'ped the source code to confirm it has rtree dependency as mentioned in other places on the internet (also see https://docs.djangoproject.com/en/2.2/ref/contrib/gis/install/spatialite/)\r\n\r\n- A careful look at config log reveals it has iconv and libxml2 dependency",
    "user": "Sinan81",
    "url": "https://api.github.com/repos/spack/spack/issues/12843",
    "updated_at": "2019-09-26 01:48:49",
    "created_at": "2019-09-17 00:58:08",
    "closed_at": "2019-09-26 01:48:49",
    "state": "closed",
    "title": "package/libspatialite: improve dependencies",
    "number": 12843,
    "milestone": null,
    "labels": [],
    "id": 494346734,
    "html_url": "https://github.com/spack/spack/pull/12843",
    "assignees": [],
    "comments": 0
}