{
    "body": "Currently dealing with some build issues: https://github.com/isl-org/Open3D/issues/4328\r\n\r\nUPDATE: successfully builds and passes all tests on macOS 10.15.7 with Python 3.8.12 and Apple Clang 12.0.0. I had to disable all the external deps to get things working. We can add these back later if the issues I opened ever get addressed.\r\n\r\n@isaaccorley",
    "user": "adamjstewart",
    "url": "https://api.github.com/repos/spack/spack/issues/27577",
    "updated_at": "2021-12-15 17:16:10",
    "created_at": "2021-11-21 22:34:09",
    "closed_at": "2021-12-15 16:34:23",
    "state": "closed",
    "title": "open3d: add new package",
    "number": 27577,
    "milestone": null,
    "labels": [
        "new-version",
        "new-package",
        "python",
        "dependencies",
        "conflicts",
        "new-variant",
        "stand-alone-tests",
        "extends"
    ],
    "id": 1059505686,
    "html_url": "https://github.com/spack/spack/pull/27577",
    "assignees": [],
    "comments": 1
}