{
    "body": "Update Julia to 1.6.2 which is the second patch release of the 1.6 series.\r\n\r\n**Changelog:**\r\n- Fix Rational{T} constructor for abstract T.\r\n- fix threadcall for new ccall lookup strategy.\r\n\r\nFull changelog can be found [here](https://github.com/JuliaLang/julia/compare/v1.6.1...v1.6.2).\r\n\r\n**Test Plan:**\r\nJulia 1.6.2 built successfully within the Autamus pipeline [here](https://github.com/autamus/registry/runs/3070414423).",
    "user": "alecbcs",
    "url": "https://api.github.com/repos/spack/spack/issues/24935",
    "updated_at": "2021-07-23 21:00:57",
    "created_at": "2021-07-16 19:00:50",
    "closed_at": "2021-07-20 04:08:38",
    "state": "closed",
    "title": "Add Julia v1.6.2",
    "number": 24935,
    "milestone": null,
    "labels": [
        "new-version",
        "update-package"
    ],
    "id": 946528194,
    "html_url": "https://github.com/spack/spack/pull/24935",
    "assignees": [],
    "comments": 3
}