{
    "body": "",
    "user": "aweits",
    "url": "https://api.github.com/repos/spack/spack/issues/19427",
    "updated_at": "2021-02-12 16:56:53",
    "created_at": "2020-10-21 11:28:42",
    "closed_at": "2020-10-21 22:09:42",
    "state": "closed",
    "title": "New package: py-fastdtw",
    "number": 19427,
    "milestone": null,
    "labels": [
        "new-package"
    ],
    "id": 726392349,
    "html_url": "https://github.com/spack/spack/pull/19427",
    "assignees": [],
    "comments": 0
}