{
    "body": "Builds on binary caching logic: ```spack install``` now installs packages from the binary cache when they are available (previously ```spack buildcache install ...``` was the only way to install specs from the build cache).\r\n\r\n- [x] Make usage of binary cache optional",
    "user": "scheibelp",
    "url": "https://api.github.com/repos/spack/spack/issues/5242",
    "updated_at": "2017-10-30 21:16:47",
    "created_at": "2017-08-30 02:40:49",
    "closed_at": "2017-10-30 21:16:47",
    "state": "closed",
    "title": "Auto install available pre-built packages from binary cache",
    "number": 5242,
    "milestone": null,
    "labels": [],
    "id": 253861296,
    "html_url": "https://github.com/spack/spack/pull/5242",
    "assignees": [],
    "comments": 5
}