{
    "body": "\u2026yaml\r\n\r\nFixes #17993\r\nIn the section \"Included configurations\",\r\ncorrect statement about precedence of multiple included configs",
    "user": "payerle",
    "url": "https://api.github.com/repos/spack/spack/issues/18663",
    "updated_at": "2021-02-19 13:59:01",
    "created_at": "2020-09-14 15:17:24",
    "closed_at": "2021-02-19 13:31:48",
    "state": "closed",
    "title": "documentation: correct statement about precedence of multiple included configs",
    "number": 18663,
    "milestone": null,
    "labels": [
        "configuration",
        "documentation"
    ],
    "id": 701196908,
    "html_url": "https://github.com/spack/spack/pull/18663",
    "assignees": [],
    "comments": 0
}