{
    "body": "Part of laristra/flecsi#235.",
    "user": "junghans",
    "url": "https://api.github.com/repos/spack/spack/issues/4000",
    "updated_at": "2017-04-27 20:10:33",
    "created_at": "2017-04-26 16:20:38",
    "closed_at": "2017-04-27 20:10:31",
    "state": "closed",
    "title": "flecsi: add mpi interoperability",
    "number": 4000,
    "milestone": null,
    "labels": [],
    "id": 224524763,
    "html_url": "https://github.com/spack/spack/pull/4000",
    "assignees": [],
    "comments": 1
}