{
    "body": "Also switches download to tarball containing `configure` script and adds post-installation tests.\r\n\r\nSuccessfully installs and passes all tests on macOS 10.15.1 with Clang 11.0.0.",
    "user": "adamjstewart",
    "url": "https://api.github.com/repos/spack/spack/issues/14134",
    "updated_at": "2019-12-14 17:56:00",
    "created_at": "2019-12-13 04:23:54",
    "closed_at": "2019-12-13 21:44:09",
    "state": "closed",
    "title": "Add latest version of jq",
    "number": 14134,
    "milestone": null,
    "labels": [
        "new-version",
        "tests"
    ],
    "id": 537341373,
    "html_url": "https://github.com/spack/spack/pull/14134",
    "assignees": [],
    "comments": 10
}